ephys_link/__about__.py
ephys_link/__init__.py
ephys_link/__main__.py
ephys_link/back_end/__init__.py
ephys_link/back_end/platform_handler.py
ephys_link/back_end/server.py
ephys_link/bindings/__init__.py
ephys_link/bindings/fake_binding.py
ephys_link/bindings/mpm_binding.py
ephys_link/bindings/parallax_binding.py
ephys_link/bindings/ump_binding.py
ephys_link/front_end/__init__.py
ephys_link/front_end/cli.py
ephys_link/front_end/console.py
ephys_link/front_end/gui.py
ephys_link/utils/__init__.py
ephys_link/utils/base_binding.py
ephys_link/utils/constants.py
ephys_link/utils/converters.py
ephys_link/utils/startup.py
ephys_link-2.2.2.dist-info/METADATA
ephys_link-2.2.2.dist-info/WHEEL
ephys_link-2.2.2.dist-info/entry_points.txt
ephys_link-2.2.2.dist-info/licenses/LICENSE
ephys_link-2.2.2.dist-info/RECORD
