Metadata-Version: 2.4
Name: ephys-link
Version: 2.2.2
Summary: A Python Socket.IO server that allows any Socket.IO-compliant application to communicate with manipulators used in electrophysiology experiments.
Project-URL: Documentation, https://virtualbrainlab.org/ephys_link/installation_and_use.html
Project-URL: Issues, https://github.com/VirtualBrainLab/ephys-link/issues
Project-URL: Source, https://github.com/VirtualBrainLab/ephys-link
Author-email: Kenneth Yang <kjy5@uw.edu>
Maintainer-email: Kenneth Yang <kjy5@uw.edu>
License-Expression: GPL-3.0-only
License-File: LICENSE
Keywords: electrophysiology,ephys,manipulator,neuroscience,neurotech,new-scale,sensapex,socket-io,virtualbrainlab
Classifier: Intended Audience :: End Users/Desktop
Classifier: Intended Audience :: Healthcare Industry
Classifier: Intended Audience :: Science/Research
Classifier: License :: OSI Approved :: GNU General Public License v3 (GPLv3)
Classifier: Operating System :: Microsoft :: Windows
Classifier: Programming Language :: Python
Classifier: Programming Language :: Python :: 3
Classifier: Programming Language :: Python :: Implementation :: CPython
Classifier: Programming Language :: Python :: Implementation :: PyPy
Classifier: Topic :: Scientific/Engineering :: Medical Science Apps.
Requires-Python: >=3.10
Requires-Dist: aiohttp==3.13.2
Requires-Dist: colorama==0.4.6
Requires-Dist: keyboard==0.13.5
Requires-Dist: packaging==25.0
Requires-Dist: platformdirs==4.5.1
Requires-Dist: pyserial==3.5
Requires-Dist: python-socketio==5.16.0
Requires-Dist: requests==2.32.5
Requires-Dist: rich==14.2.0
Requires-Dist: sensapex==1.504.1
Requires-Dist: vbl-aquarium==1.2.0
